starccato/__init__.py
starccato/cli.py
starccato/defaults.py
starccato/logger.py
starccato/plotting.py
starccato/utils.py
starccato/nn/__init__.py
starccato/nn/save_load_models.py
starccato/nn/discriminator/__init__.py
starccato/nn/discriminator/dcgan_discriminator.py
starccato/nn/generator/__init__.py
starccato/nn/generator/dcgan_generator.py
starccato/training/__init__.py
starccato/training/trainer.py
starccato/training/training_data.py
starccato-0.0.2.dist-info/LICENSE
starccato-0.0.2.dist-info/METADATA
starccato-0.0.2.dist-info/WHEEL
starccato-0.0.2.dist-info/entry_points.txt
starccato-0.0.2.dist-info/top_level.txt
starccato-0.0.2.dist-info/RECORD
