Metadata-Version: 2.1
Name: starccato
Version: 0.0.2
Summary: Starccato is a fast stellar core-collapse gravitational wave generator.
Author-email: Tarin Eccleston <tarin.eccleston@gmail.com>, Matthew Edwards <matt.edwards@auckland.ac.nz>
Project-URL: Homepage, https://github.com/starccato/starccato
Project-URL: Bug Reports, https://github.com/starccato/starccato
Project-URL: Source, https://github.com/starccato/starccato
Classifier: Development Status :: 3 - Alpha
Classifier: Intended Audience :: Science/Research
Classifier: License :: OSI Approved :: MIT License
Classifier: Operating System :: OS Independent
Classifier: Programming Language :: Python :: 3.8
Requires-Python: >=3.8
License-File: LICENSE
Requires-Dist: scikit-learn >=1.3.2
Requires-Dist: torch >=2.0.1
Requires-Dist: torchsummary >=1.5.1
Requires-Dist: torchvision >=0.15.2
Requires-Dist: pandas
Requires-Dist: click
Requires-Dist: loguru
Requires-Dist: matplotlib
Requires-Dist: tqdm
Provides-Extra: dev
Requires-Dist: pytest >=6.0 ; extra == 'dev'
Requires-Dist: pytest-click ; extra == 'dev'
Requires-Dist: pytest-cov >=4.1.0 ; extra == 'dev'
Requires-Dist: coverage[toml] ; extra == 'dev'
Requires-Dist: pre-commit ; extra == 'dev'
Requires-Dist: flake8 >=5.0.4 ; extra == 'dev'
Requires-Dist: black ==22.10.0 ; extra == 'dev'
Requires-Dist: jupyter-book ; extra == 'dev'
